projectmaker/__init__.py
projectmaker/commands.py
projectmaker/config.py
projectmaker/config.yaml
projectmaker/main.py
projectmaker-0.1.1.dist-info/LICENSE
projectmaker-0.1.1.dist-info/METADATA
projectmaker-0.1.1.dist-info/WHEEL
projectmaker-0.1.1.dist-info/entry_points.txt
projectmaker-0.1.1.dist-info/top_level.txt
projectmaker-0.1.1.dist-info/RECORD
